wikimedia_enterprise_mcp/__init__.py
wikimedia_enterprise_mcp/__main__.py
wikimedia_enterprise_mcp/constants.py
wikimedia_enterprise_mcp/py.typed
wikimedia_enterprise_mcp/server.py
wikimedia_enterprise_mcp/util.py
wikimedia_enterprise_mcp/wikidata.py
wikimedia_enterprise_mcp/wme.py
wikimedia_enterprise_mcp-0.1.7.dist-info/LICENSE
wikimedia_enterprise_mcp-0.1.7.dist-info/METADATA
wikimedia_enterprise_mcp-0.1.7.dist-info/WHEEL
wikimedia_enterprise_mcp-0.1.7.dist-info/entry_points.txt
wikimedia_enterprise_mcp-0.1.7.dist-info/RECORD
