Metadata-Version: 2.1
Name: wikimedia-enterprise-mcp
Version: 0.1.7
Summary: implementation of the model context protocol for the wikimedia enterprise api and wikibase REST API
Home-page: https://gitlab.wikimedia.org/repos/future-audiences/wikimedia-enterprise-model-context-protocol
License: MIT
Keywords: wikimedia,wikidata,wikipedia,mcp
Author: Daniel Erenrich
Author-email: derenrich@wikimedia.org
Requires-Python: >=3.11,<4.0
Classifier: Development Status :: 4 - Beta
Classifier: Intended Audience :: Developers
Classifier: License :: OSI Approved :: MIT License
Classifier: Operating System :: OS Independent
Classifier: Programming Language :: Python :: 3
Classifier: Programming Language :: Python :: 3.11
Classifier: Programming Language :: Python :: 3.12
Classifier: Programming Language :: Python :: 3.13
Requires-Dist: asyncer (>=0.0.8,<0.0.9)
Requires-Dist: mcp (>=1.0.0,<2.0.0)
Requires-Dist: mediawikiapi (>=1.2,<2.0)
Requires-Dist: python-dotenv (>=1.0.1,<2.0.0)
Requires-Dist: wiki2md (>=0.1.3,<0.2.0)
Requires-Dist: wikibase-rest-api-client (>=0.2.2,<0.3.0)
Requires-Dist: wme (>=0.1.0,<0.2.0)
Project-URL: Repository, https://gitlab.wikimedia.org/repos/future-audiences/wikimedia-enterprise-model-context-protocol
